lndhub/__init__.py
lndhub/exceptions.py
lndhub/models.py
lndhub/utils.py
lndhub-0.0.2.dist-info/LICENSE
lndhub-0.0.2.dist-info/METADATA
lndhub-0.0.2.dist-info/WHEEL
lndhub-0.0.2.dist-info/top_level.txt
lndhub-0.0.2.dist-info/RECORD
