Metadata-Version: 2.1
Name: lndhub
Version: 0.0.2
Summary: UNKNOWN
Home-page: https://github.com/eillarra/lndhub
Author: eillarra
Author-email: eneko@illarra.com
License: MIT
Keywords: bitcoin lightning-network lndhub lnurl
Platform: UNKNOWN
Classifier: Development Status :: 1 - Planning
Classifier: Intended Audience :: Developers
Classifier: License :: OSI Approved :: MIT License
Classifier: Operating System :: OS Independent
Classifier: Programming Language :: Python
Classifier: Programming Language :: Python :: 3.6
Classifier: Programming Language :: Python :: 3.7
Classifier: Programming Language :: Python :: 3.8
Classifier: Topic :: Utilities
Requires-Dist: requests
